{"id":"EfcLDDAkyqguXw9Vbtcae7fRhxCsY1chPUMEWH5LU7fWMD4xkmdyS5WLyFAeWwxZYS5oE3WoohKSgyEQNHxKBergZHmnu","title":"top scoring links : AdGuardHome","displayTitle":"Reddit - AdGuard Home","url":"https://www.reddit.com/r/adguardhome/top/.rss?sort=top&t=day&limit=6","feedLink":"https://www.reddit.com/r/adguardhome/top/?sort=top&t=day&limit=6","isQuery":false,"isEmpty":false,"isHidden":false,"items":[{"title":"Which domains to block for LG's WebOS?","url":"https://www.reddit.com/r/AdGuardHome/comments/1i0gfic/which_domains_to_block_for_lgs_webos/","date":1736781995,"author":"/u/yellowroll","unread":true,"content":"<!-- SC_OFF --><div class=\"md\"><p>I am based in the UK and wish to block update pop-ups, trending and recommendations bar on the home screen, sport scores, and other useless junk from the home screen. I still wish to use the voice assistant, so don&#39;t want that feature blocked.</p> </div><!-- SC_ON --> &#32; submitted by &#32; <a href=\"https://www.reddit.com/user/yellowroll\"> /u/yellowroll </a> <br/> <span><a href=\"https://www.reddit.com/r/AdGuardHome/comments/1i0gfic/which_domains_to_block_for_lgs_webos/\">[link]</a></span> &#32; <span><a href=\"https://www.reddit.com/r/AdGuardHome/comments/1i0gfic/which_domains_to_block_for_lgs_webos/\">[comments]</a></span>","flags":null,"enclosureUrl":"","enclosureMime":""}]}